{
    "dicetoorderedhand.py": [
        {
            "operation": "DELETE",
            "lines": 0,
            "keyStrokeTimeStamp": "Mon Jul 12 2021 22:07:27",
            "keyStrokeInfo": "",
            "position": "15,2"
        },
        {
            "operation": "DELETE",
            "lines": 0,
            "keyStrokeTimeStamp": "Mon Jul 12 2021 22:07:30",
            "keyStrokeInfo": "",
            "position": "15,1"
        },
        {
            "operation": "TYPED",
            "lines": 0,
            "keyStrokeTimeStamp": "Mon Jul 12 2021 22:07:31",
            "keyStrokeInfo": "\r\n",
            "position": "15,1"
        },
        {
            "operation": "DELETE",
            "lines": 1,
            "keyStrokeTimeStamp": "Mon Jul 12 2021 22:07:32",
            "keyStrokeInfo": "",
            "position": "15,1"
        },
        {
            "operation": "DELETE",
            "lines": 1,
            "keyStrokeTimeStamp": "Mon Jul 12 2021 22:07:32",
            "keyStrokeInfo": "",
            "position": "14,23"
        },
        {
            "operation": "TYPED",
            "lines": 0,
            "keyStrokeTimeStamp": "Mon Jul 12 2021 22:07:33",
            "keyStrokeInfo": "\r\n\t",
            "position": "14,23"
        },
        {
            "operation": "TYPED",
            "lines": 0,
            "keyStrokeTimeStamp": "Mon Jul 12 2021 22:07:35",
            "keyStrokeInfo": "p",
            "position": "15,2"
        },
        {
            "operation": "TYPED",
            "lines": 0,
            "keyStrokeTimeStamp": "Mon Jul 12 2021 22:07:35",
            "keyStrokeInfo": "a",
            "position": "15,3"
        },
        {
            "operation": "TYPED",
            "lines": 0,
            "keyStrokeTimeStamp": "Mon Jul 12 2021 22:07:35",
            "keyStrokeInfo": "s",
            "position": "15,4"
        },
        {
            "operation": "TYPED",
            "lines": 0,
            "keyStrokeTimeStamp": "Mon Jul 12 2021 22:07:36",
            "keyStrokeInfo": "s",
            "position": "15,5"
        },
        {
            "operation": "TYPED",
            "lines": 0,
            "keyStrokeTimeStamp": "Mon Jul 12 2021 22:07:37",
            "keyStrokeInfo": "pass",
            "position": "15,2"
        },
        {
            "operation": "DELETE",
            "lines": 0,
            "keyStrokeTimeStamp": "Tue Jul 13 2021 08:57:01",
            "keyStrokeInfo": "",
            "position": "15,5"
        },
        {
            "operation": "DELETE",
            "lines": 0,
            "keyStrokeTimeStamp": "Tue Jul 13 2021 08:57:01",
            "keyStrokeInfo": "",
            "position": "15,4"
        },
        {
            "operation": "DELETE",
            "lines": 0,
            "keyStrokeTimeStamp": "Tue Jul 13 2021 08:57:01",
            "keyStrokeInfo": "",
            "position": "15,3"
        },
        {
            "operation": "DELETE",
            "lines": 0,
            "keyStrokeTimeStamp": "Tue Jul 13 2021 08:57:02",
            "keyStrokeInfo": "",
            "position": "15,2"
        },
        {
            "operation": "TYPED",
            "lines": 0,
            "keyStrokeTimeStamp": "Tue Jul 13 2021 08:57:03",
            "keyStrokeInfo": "l",
            "position": "15,2"
        },
        {
            "operation": "TYPED",
            "lines": 0,
            "keyStrokeTimeStamp": "Tue Jul 13 2021 08:57:04",
            "keyStrokeInfo": " ",
            "position": "15,3"
        },
        {
            "operation": "TYPED",
            "lines": 0,
            "keyStrokeTimeStamp": "Tue Jul 13 2021 08:57:05",
            "keyStrokeInfo": "=",
            "position": "15,4"
        },
        {
            "operation": "TYPED",
            "lines": 0,
            "keyStrokeTimeStamp": "Tue Jul 13 2021 08:57:05",
            "keyStrokeInfo": " ",
            "position": "15,5"
        },
        {
            "operation": "TYPED",
            "lines": 0,
            "keyStrokeTimeStamp": "Tue Jul 13 2021 08:57:06",
            "keyStrokeInfo": "[]",
            "position": "15,6"
        },
        {
            "operation": "TYPED",
            "lines": 0,
            "keyStrokeTimeStamp": "Tue Jul 13 2021 08:57:10",
            "keyStrokeInfo": "a",
            "position": "15,7"
        },
        {
            "operation": "TYPED",
            "lines": 0,
            "keyStrokeTimeStamp": "Tue Jul 13 2021 08:57:10",
            "keyStrokeInfo": ",",
            "position": "15,8"
        },
        {
            "operation": "TYPED",
            "lines": 0,
            "keyStrokeTimeStamp": "Tue Jul 13 2021 08:57:10",
            "keyStrokeInfo": "b",
            "position": "15,9"
        },
        {
            "operation": "TYPED",
            "lines": 0,
            "keyStrokeTimeStamp": "Tue Jul 13 2021 08:57:11",
            "keyStrokeInfo": ",",
            "position": "15,10"
        },
        {
            "operation": "TYPED",
            "lines": 0,
            "keyStrokeTimeStamp": "Tue Jul 13 2021 08:57:12",
            "keyStrokeInfo": "c",
            "position": "15,11"
        },
        {
            "operation": "TYPED",
            "lines": 0,
            "keyStrokeTimeStamp": "Tue Jul 13 2021 08:57:13",
            "keyStrokeInfo": "\r\n\t",
            "position": "15,13"
        },
        {
            "operation": "TYPED",
            "lines": 0,
            "keyStrokeTimeStamp": "Tue Jul 13 2021 08:57:19",
            "keyStrokeInfo": "l",
            "position": "16,2"
        },
        {
            "operation": "TYPED",
            "lines": 0,
            "keyStrokeTimeStamp": "Tue Jul 13 2021 08:57:19",
            "keyStrokeInfo": ".",
            "position": "16,3"
        },
        {
            "operation": "TYPED",
            "lines": 0,
            "keyStrokeTimeStamp": "Tue Jul 13 2021 08:57:21",
            "keyStrokeInfo": "s",
            "position": "16,4"
        },
        {
            "operation": "TYPED",
            "lines": 0,
            "keyStrokeTimeStamp": "Tue Jul 13 2021 08:57:22",
            "keyStrokeInfo": "sort",
            "position": "16,4"
        },
        {
            "operation": "TYPED",
            "lines": 0,
            "keyStrokeTimeStamp": "Tue Jul 13 2021 08:57:23",
            "keyStrokeInfo": "()",
            "position": "16,8"
        },
        {
            "operation": "TYPED",
            "lines": 0,
            "keyStrokeTimeStamp": "Tue Jul 13 2021 08:57:24",
            "keyStrokeInfo": "r",
            "position": "16,9"
        },
        {
            "operation": "TYPED",
            "lines": 0,
            "keyStrokeTimeStamp": "Tue Jul 13 2021 08:57:24",
            "keyStrokeInfo": "e",
            "position": "16,10"
        },
        {
            "operation": "TYPED",
            "lines": 0,
            "keyStrokeTimeStamp": "Tue Jul 13 2021 08:57:24",
            "keyStrokeInfo": "v",
            "position": "16,11"
        },
        {
            "operation": "TYPED",
            "lines": 0,
            "keyStrokeTimeStamp": "Tue Jul 13 2021 08:57:24",
            "keyStrokeInfo": "e",
            "position": "16,12"
        },
        {
            "operation": "TYPED",
            "lines": 0,
            "keyStrokeTimeStamp": "Tue Jul 13 2021 08:57:25",
            "keyStrokeInfo": "reverse=",
            "position": "16,9"
        },
        {
            "operation": "TYPED",
            "lines": 0,
            "keyStrokeTimeStamp": "Tue Jul 13 2021 08:57:26",
            "keyStrokeInfo": "t",
            "position": "16,17"
        },
        {
            "operation": "TYPED",
            "lines": 0,
            "keyStrokeTimeStamp": "Tue Jul 13 2021 08:57:27",
            "keyStrokeInfo": "r",
            "position": "16,18"
        },
        {
            "operation": "TYPED",
            "lines": 0,
            "keyStrokeTimeStamp": "Tue Jul 13 2021 08:57:28",
            "keyStrokeInfo": "True",
            "position": "16,17"
        },
        {
            "operation": "TYPED",
            "lines": 0,
            "keyStrokeTimeStamp": "Tue Jul 13 2021 08:57:37",
            "keyStrokeInfo": "\r\n\t",
            "position": "16,22"
        },
        {
            "operation": "TYPED",
            "lines": 0,
            "keyStrokeTimeStamp": "Tue Jul 13 2021 08:57:40",
            "keyStrokeInfo": "s",
            "position": "17,2"
        },
        {
            "operation": "TYPED",
            "lines": 0,
            "keyStrokeTimeStamp": "Tue Jul 13 2021 08:57:40",
            "keyStrokeInfo": "t",
            "position": "17,3"
        },
        {
            "operation": "TYPED",
            "lines": 0,
            "keyStrokeTimeStamp": "Tue Jul 13 2021 08:57:40",
            "keyStrokeInfo": "r",
            "position": "17,4"
        },
        {
            "operation": "TYPED",
            "lines": 0,
            "keyStrokeTimeStamp": "Tue Jul 13 2021 08:57:43",
            "keyStrokeInfo": "i",
            "position": "17,5"
        },
        {
            "operation": "TYPED",
            "lines": 0,
            "keyStrokeTimeStamp": "Tue Jul 13 2021 08:57:43",
            "keyStrokeInfo": "n",
            "position": "17,6"
        },
        {
            "operation": "TYPED",
            "lines": 0,
            "keyStrokeTimeStamp": "Tue Jul 13 2021 08:57:44",
            "keyStrokeInfo": "g",
            "position": "17,7"
        },
        {
            "operation": "TYPED",
            "lines": 0,
            "keyStrokeTimeStamp": "Tue Jul 13 2021 08:57:44",
            "keyStrokeInfo": "s",
            "position": "17,8"
        },
        {
            "operation": "TYPED",
            "lines": 0,
            "keyStrokeTimeStamp": "Tue Jul 13 2021 08:57:46",
            "keyStrokeInfo": " ",
            "position": "17,9"
        },
        {
            "operation": "TYPED",
            "lines": 0,
            "keyStrokeTimeStamp": "Tue Jul 13 2021 08:57:46",
            "keyStrokeInfo": "=",
            "position": "17,10"
        },
        {
            "operation": "TYPED",
            "lines": 0,
            "keyStrokeTimeStamp": "Tue Jul 13 2021 08:57:48",
            "keyStrokeInfo": " ",
            "position": "17,11"
        },
        {
            "operation": "TYPED",
            "lines": 0,
            "keyStrokeTimeStamp": "Tue Jul 13 2021 08:57:49",
            "keyStrokeInfo": "[]",
            "position": "17,12"
        },
        {
            "operation": "TYPED",
            "lines": 0,
            "keyStrokeTimeStamp": "Tue Jul 13 2021 08:57:49",
            "keyStrokeInfo": "s",
            "position": "17,13"
        },
        {
            "operation": "TYPED",
            "lines": 0,
            "keyStrokeTimeStamp": "Tue Jul 13 2021 08:57:50",
            "keyStrokeInfo": "t",
            "position": "17,14"
        },
        {
            "operation": "TYPED",
            "lines": 0,
            "keyStrokeTimeStamp": "Tue Jul 13 2021 08:57:50",
            "keyStrokeInfo": "r",
            "position": "17,15"
        },
        {
            "operation": "TYPED",
            "lines": 0,
            "keyStrokeTimeStamp": "Tue Jul 13 2021 08:57:51",
            "keyStrokeInfo": "()",
            "position": "17,16"
        },
        {
            "operation": "TYPED",
            "lines": 0,
            "keyStrokeTimeStamp": "Tue Jul 13 2021 08:57:52",
            "keyStrokeInfo": "i",
            "position": "17,17"
        },
        {
            "operation": "TYPED",
            "lines": 0,
            "keyStrokeTimeStamp": "Tue Jul 13 2021 08:57:54",
            "keyStrokeInfo": " ",
            "position": "17,19"
        },
        {
            "operation": "TYPED",
            "lines": 0,
            "keyStrokeTimeStamp": "Tue Jul 13 2021 08:57:55",
            "keyStrokeInfo": "f",
            "position": "17,20"
        },
        {
            "operation": "TYPED",
            "lines": 0,
            "keyStrokeTimeStamp": "Tue Jul 13 2021 08:57:55",
            "keyStrokeInfo": "o",
            "position": "17,21"
        },
        {
            "operation": "TYPED",
            "lines": 0,
            "keyStrokeTimeStamp": "Tue Jul 13 2021 08:57:55",
            "keyStrokeInfo": "r",
            "position": "17,22"
        },
        {
            "operation": "TYPED",
            "lines": 0,
            "keyStrokeTimeStamp": "Tue Jul 13 2021 08:57:55",
            "keyStrokeInfo": " ",
            "position": "17,23"
        },
        {
            "operation": "TYPED",
            "lines": 0,
            "keyStrokeTimeStamp": "Tue Jul 13 2021 08:57:56",
            "keyStrokeInfo": "i",
            "position": "17,24"
        },
        {
            "operation": "TYPED",
            "lines": 0,
            "keyStrokeTimeStamp": "Tue Jul 13 2021 08:57:56",
            "keyStrokeInfo": " ",
            "position": "17,25"
        },
        {
            "operation": "TYPED",
            "lines": 0,
            "keyStrokeTimeStamp": "Tue Jul 13 2021 08:57:56",
            "keyStrokeInfo": "i",
            "position": "17,26"
        },
        {
            "operation": "TYPED",
            "lines": 0,
            "keyStrokeTimeStamp": "Tue Jul 13 2021 08:57:57",
            "keyStrokeInfo": "n",
            "position": "17,27"
        },
        {
            "operation": "TYPED",
            "lines": 0,
            "keyStrokeTimeStamp": "Tue Jul 13 2021 08:57:57",
            "keyStrokeInfo": " ",
            "position": "17,28"
        },
        {
            "operation": "TYPED",
            "lines": 0,
            "keyStrokeTimeStamp": "Tue Jul 13 2021 08:57:58",
            "keyStrokeInfo": "l",
            "position": "17,29"
        },
        {
            "operation": "TYPED",
            "lines": 0,
            "keyStrokeTimeStamp": "Tue Jul 13 2021 08:58:01",
            "keyStrokeInfo": "\r\n\t",
            "position": "17,31"
        },
        {
            "operation": "TYPED",
            "lines": 0,
            "keyStrokeTimeStamp": "Tue Jul 13 2021 08:58:02",
            "keyStrokeInfo": "s",
            "position": "18,2"
        },
        {
            "operation": "TYPED",
            "lines": 0,
            "keyStrokeTimeStamp": "Tue Jul 13 2021 08:58:03",
            "keyStrokeInfo": "t",
            "position": "18,3"
        },
        {
            "operation": "TYPED",
            "lines": 0,
            "keyStrokeTimeStamp": "Tue Jul 13 2021 08:58:03",
            "keyStrokeInfo": "r",
            "position": "18,4"
        },
        {
            "operation": "TYPED",
            "lines": 0,
            "keyStrokeTimeStamp": "Tue Jul 13 2021 08:58:03",
            "keyStrokeInfo": "i",
            "position": "18,5"
        },
        {
            "operation": "TYPED",
            "lines": 0,
            "keyStrokeTimeStamp": "Tue Jul 13 2021 08:58:03",
            "keyStrokeInfo": "n",
            "position": "18,6"
        },
        {
            "operation": "TYPED",
            "lines": 0,
            "keyStrokeTimeStamp": "Tue Jul 13 2021 08:58:04",
            "keyStrokeInfo": "g",
            "position": "18,7"
        },
        {
            "operation": "TYPED",
            "lines": 0,
            "keyStrokeTimeStamp": "Tue Jul 13 2021 08:58:04",
            "keyStrokeInfo": "s",
            "position": "18,8"
        },
        {
            "operation": "TYPED",
            "lines": 0,
            "keyStrokeTimeStamp": "Tue Jul 13 2021 08:58:04",
            "keyStrokeInfo": " ",
            "position": "18,9"
        },
        {
            "operation": "TYPED",
            "lines": 0,
            "keyStrokeTimeStamp": "Tue Jul 13 2021 08:58:05",
            "keyStrokeInfo": "=",
            "position": "18,10"
        },
        {
            "operation": "TYPED",
            "lines": 0,
            "keyStrokeTimeStamp": "Tue Jul 13 2021 08:58:05",
            "keyStrokeInfo": " ",
            "position": "18,11"
        },
        {
            "operation": "TYPED",
            "lines": 0,
            "keyStrokeTimeStamp": "Tue Jul 13 2021 08:58:07",
            "keyStrokeInfo": "\"\"",
            "position": "18,12"
        },
        {
            "operation": "TYPED",
            "lines": 0,
            "keyStrokeTimeStamp": "Tue Jul 13 2021 08:58:09",
            "keyStrokeInfo": ".",
            "position": "18,14"
        },
        {
            "operation": "TYPED",
            "lines": 0,
            "keyStrokeTimeStamp": "Tue Jul 13 2021 08:58:09",
            "keyStrokeInfo": "j",
            "position": "18,15"
        },
        {
            "operation": "TYPED",
            "lines": 0,
            "keyStrokeTimeStamp": "Tue Jul 13 2021 08:58:10",
            "keyStrokeInfo": "o",
            "position": "18,16"
        },
        {
            "operation": "TYPED",
            "lines": 0,
            "keyStrokeTimeStamp": "Tue Jul 13 2021 08:58:10",
            "keyStrokeInfo": "i",
            "position": "18,17"
        },
        {
            "operation": "TYPED",
            "lines": 0,
            "keyStrokeTimeStamp": "Tue Jul 13 2021 08:58:10",
            "keyStrokeInfo": "n",
            "position": "18,18"
        },
        {
            "operation": "TYPED",
            "lines": 0,
            "keyStrokeTimeStamp": "Tue Jul 13 2021 08:58:12",
            "keyStrokeInfo": "()",
            "position": "18,19"
        },
        {
            "operation": "TYPED",
            "lines": 0,
            "keyStrokeTimeStamp": "Tue Jul 13 2021 08:58:13",
            "keyStrokeInfo": "s",
            "position": "18,20"
        },
        {
            "operation": "TYPED",
            "lines": 0,
            "keyStrokeTimeStamp": "Tue Jul 13 2021 08:58:13",
            "keyStrokeInfo": "t",
            "position": "18,21"
        },
        {
            "operation": "TYPED",
            "lines": 0,
            "keyStrokeTimeStamp": "Tue Jul 13 2021 08:58:13",
            "keyStrokeInfo": "r",
            "position": "18,22"
        },
        {
            "operation": "TYPED",
            "lines": 0,
            "keyStrokeTimeStamp": "Tue Jul 13 2021 08:58:14",
            "keyStrokeInfo": "i",
            "position": "18,23"
        },
        {
            "operation": "TYPED",
            "lines": 0,
            "keyStrokeTimeStamp": "Tue Jul 13 2021 08:58:14",
            "keyStrokeInfo": "n",
            "position": "18,24"
        },
        {
            "operation": "TYPED",
            "lines": 0,
            "keyStrokeTimeStamp": "Tue Jul 13 2021 08:58:14",
            "keyStrokeInfo": "g",
            "position": "18,25"
        },
        {
            "operation": "TYPED",
            "lines": 0,
            "keyStrokeTimeStamp": "Tue Jul 13 2021 08:58:14",
            "keyStrokeInfo": "s",
            "position": "18,26"
        },
        {
            "operation": "TYPED",
            "lines": 0,
            "keyStrokeTimeStamp": "Tue Jul 13 2021 08:58:17",
            "keyStrokeInfo": "\r\n\t",
            "position": "18,28"
        },
        {
            "operation": "TYPED",
            "lines": 0,
            "keyStrokeTimeStamp": "Tue Jul 13 2021 08:58:17",
            "keyStrokeInfo": "r",
            "position": "19,2"
        },
        {
            "operation": "TYPED",
            "lines": 0,
            "keyStrokeTimeStamp": "Tue Jul 13 2021 08:58:17",
            "keyStrokeInfo": "e",
            "position": "19,3"
        },
        {
            "operation": "TYPED",
            "lines": 0,
            "keyStrokeTimeStamp": "Tue Jul 13 2021 08:58:18",
            "keyStrokeInfo": "t",
            "position": "19,4"
        },
        {
            "operation": "TYPED",
            "lines": 0,
            "keyStrokeTimeStamp": "Tue Jul 13 2021 08:58:18",
            "keyStrokeInfo": "u",
            "position": "19,5"
        },
        {
            "operation": "TYPED",
            "lines": 0,
            "keyStrokeTimeStamp": "Tue Jul 13 2021 08:58:18",
            "keyStrokeInfo": "r",
            "position": "19,6"
        },
        {
            "operation": "TYPED",
            "lines": 0,
            "keyStrokeTimeStamp": "Tue Jul 13 2021 08:58:18",
            "keyStrokeInfo": "n",
            "position": "19,7"
        },
        {
            "operation": "TYPED",
            "lines": 0,
            "keyStrokeTimeStamp": "Tue Jul 13 2021 08:58:19",
            "keyStrokeInfo": " ",
            "position": "19,8"
        },
        {
            "operation": "TYPED",
            "lines": 0,
            "keyStrokeTimeStamp": "Tue Jul 13 2021 08:58:20",
            "keyStrokeInfo": "i",
            "position": "19,9"
        },
        {
            "operation": "TYPED",
            "lines": 0,
            "keyStrokeTimeStamp": "Tue Jul 13 2021 08:58:21",
            "keyStrokeInfo": "n",
            "position": "19,10"
        },
        {
            "operation": "TYPED",
            "lines": 0,
            "keyStrokeTimeStamp": "Tue Jul 13 2021 08:58:21",
            "keyStrokeInfo": "t",
            "position": "19,11"
        },
        {
            "operation": "TYPED",
            "lines": 0,
            "keyStrokeTimeStamp": "Tue Jul 13 2021 08:58:22",
            "keyStrokeInfo": "()",
            "position": "19,12"
        },
        {
            "operation": "TYPED",
            "lines": 0,
            "keyStrokeTimeStamp": "Tue Jul 13 2021 08:58:23",
            "keyStrokeInfo": "s",
            "position": "19,13"
        },
        {
            "operation": "TYPED",
            "lines": 0,
            "keyStrokeTimeStamp": "Tue Jul 13 2021 08:58:23",
            "keyStrokeInfo": "t",
            "position": "19,14"
        },
        {
            "operation": "TYPED",
            "lines": 0,
            "keyStrokeTimeStamp": "Tue Jul 13 2021 08:58:23",
            "keyStrokeInfo": "r",
            "position": "19,15"
        },
        {
            "operation": "TYPED",
            "lines": 0,
            "keyStrokeTimeStamp": "Tue Jul 13 2021 08:58:23",
            "keyStrokeInfo": "i",
            "position": "19,16"
        },
        {
            "operation": "TYPED",
            "lines": 0,
            "keyStrokeTimeStamp": "Tue Jul 13 2021 08:58:24",
            "keyStrokeInfo": "n",
            "position": "19,17"
        },
        {
            "operation": "TYPED",
            "lines": 0,
            "keyStrokeTimeStamp": "Tue Jul 13 2021 08:58:24",
            "keyStrokeInfo": "g",
            "position": "19,18"
        },
        {
            "operation": "DELETE",
            "lines": 0,
            "keyStrokeTimeStamp": "Tue Jul 13 2021 08:58:35",
            "keyStrokeInfo": "",
            "position": "18,8"
        }
    ]
}